README.txt
setup.py
boois_json_encoder/__init__.py
boois_json_encoder/json_encoder.py
boois_json_encoder.egg-info/PKG-INFO
boois_json_encoder.egg-info/SOURCES.txt
boois_json_encoder.egg-info/dependency_links.txt
boois_json_encoder.egg-info/top_level.txt
boois_json_encoder.egg-info/zip-safe