Metadata-Version: 1.1
Name: boois-json-encoder
Version: 1.0.0
Summary: boois_json_encoder
Home-page: http://www.boois.cn/
Author: boois
Author-email: admin@boois.cn
License: MIT
Keywords: boois_json_encoder
Platform: UNKNOWN
Classifier: License :: OSI Approved :: MIT License
Classifier: Programming Language :: Python
Classifier: Intended Audience :: Developers
Classifier: Operating System :: OS Independent
